{
  "filename": "FPCN19.TXT",
  "size": 6514,
  "timestamp_utc": 1773182842,
  "product": {
    "source": "wmo_unsupported_bulletin",
    "family": "unsupported_wmo_bulletin",
    "container": "raw",
    "wmo_header": {
      "ttaaii": "FPCN19",
      "cccc": "CWVR",
      "ddhhmm": "102245",
      "bbb": null
    },
    "issues": [
      {
        "kind": "wmo_bulletin_parse",
        "code": "unsupported_canadian_text_bulletin",
        "message": "recognized valid WMO Canadian text bulletin, but parsing is not implemented",
        "line": "FORECASTS FOR NORTHERN, CENTRAL, SOUTHWESTERN YUKON AND NORTHWESTERN"
      }
    ]
  }
}